draco/__init__.py
draco/benchmark.py
draco/db.py
draco/demo.py
draco/metrics.py
draco/pipeline.py
draco/results.py
draco/targets.py
draco/utils.py
draco/loaders/__init__.py
draco/loaders/csv.py
draco/pipelines/double_lstm/double_lstm.json
draco/pipelines/double_lstm/double_lstm_prob.json
draco/pipelines/double_lstm/double_lstm_prob_with_unstack.json
draco/pipelines/double_lstm/double_lstm_with_unstack.json
draco/pipelines/dummy/dummy.json
draco/pipelines/lstm/lstm.json
draco/pipelines/lstm/lstm_prob.json
draco/pipelines/lstm/lstm_prob_with_unstack.json
draco/pipelines/lstm/lstm_with_unstack.json
draco/pipelines/lstm_regressor/lstm_regressor.json
draco/pipelines/lstm_regressor/lstm_regressor_with_unstack.json
draco/primitives/mlblocks.MLPipeline.json
draco/primitives/numpy.take.json
draco/primitives/xgboost.XGBClassifier:probabilities.json
draco_ml-0.3.0.dist-info/AUTHORS.rst
draco_ml-0.3.0.dist-info/LICENSE
draco_ml-0.3.0.dist-info/METADATA
draco_ml-0.3.0.dist-info/WHEEL
draco_ml-0.3.0.dist-info/entry_points.txt
draco_ml-0.3.0.dist-info/top_level.txt
draco_ml-0.3.0.dist-info/RECORD
